{
  "updated_at": "2026-04-28T07:18:59Z",
  "releases": [
    {
      "tag": "v0.40.2",
      "published": "2026-04-28T05:25:11Z",
      "total": 2,
      "update_checks": 5,
      "assets": [
        {
          "name": "Kirodex_0.40.2_aarch64.dmg",
          "downloads": 1,
          "platform": "macos"
        },
        {
          "name": "Kirodex_0.40.2_amd64.AppImage",
          "downloads": 0,
          "platform": "linux"
        },
        {
          "name": "Kirodex_0.40.2_amd64.AppImage.tar.gz",
          "downloads": 0,
          "platform": "linux"
        },
        {
          "name": "Kirodex_0.40.2_amd64.deb",
          "downloads": 0,
          "platform": "linux"
        },
        {
          "name": "Kirodex_0.40.2_x64-setup.exe",
          "downloads": 0,
          "platform": "windows"
        },
        {
          "name": "Kirodex_0.40.2_x64-setup.nsis.zip",
          "downloads": 0,
          "platform": "windows"
        },
        {
          "name": "Kirodex_aarch64.app.tar.gz",
          "downloads": 1,
          "platform": "macos"
        }
      ]
    },
    {
      "tag": "v0.40.1",
      "published": "2026-04-27T22:20:38Z",
      "total": 2,
      "update_checks": 21,
      "assets": [
        {
          "name": "Kirodex_0.40.1_aarch64.dmg",
          "downloads": 1,
          "platform": "macos"
        },
        {
          "name": "Kirodex_0.40.1_amd64.AppImage",
          "downloads": 0,
          "platform": "linux"
        },
        {
          "name": "Kirodex_0.40.1_amd64.AppImage.tar.gz",
          "downloads": 0,
          "platform": "linux"
        },
        {
          "name": "Kirodex_0.40.1_amd64.deb",
          "downloads": 0,
          "platform": "linux"
        },
        {
          "name": "Kirodex_0.40.1_x64-setup.exe",
          "downloads": 0,
          "platform": "windows"
        },
        {
          "name": "Kirodex_0.40.1_x64-setup.nsis.zip",
          "downloads": 0,
          "platform": "windows"
        },
        {
          "name": "Kirodex_aarch64.app.tar.gz",
          "downloads": 1,
          "platform": "macos"
        }
      ]
    },
    {
      "tag": "v0.40.0",
      "published": "2026-04-27T22:16:02Z",
      "total": 2,
      "update_checks": 0,
      "assets": [
        {
          "name": "Kirodex_0.40.0_aarch64.dmg",
          "downloads": 1,
          "platform": "macos"
        },
        {
          "name": "Kirodex_0.40.0_amd64.AppImage",
          "downloads": 0,
          "platform": "linux"
        },
        {
          "name": "Kirodex_0.40.0_amd64.AppImage.tar.gz",
          "downloads": 0,
          "platform": "linux"
        },
        {
          "name": "Kirodex_0.40.0_amd64.deb",
          "downloads": 0,
          "platform": "linux"
        },
        {
          "name": "Kirodex_0.40.0_x64-setup.exe",
          "downloads": 0,
          "platform": "windows"
        },
        {
          "name": "Kirodex_0.40.0_x64-setup.nsis.zip",
          "downloads": 0,
          "platform": "windows"
        },
        {
          "name": "Kirodex_aarch64.app.tar.gz",
          "downloads": 1,
          "platform": "macos"
        }
      ]
    },
    {
      "tag": "v0.39.0",
      "published": "2026-04-27T11:39:36Z",
      "total": 3,
      "update_checks": 40,
      "assets": [
        {
          "name": "Kirodex_0.39.0_aarch64.dmg",
          "downloads": 1,
          "platform": "macos"
        },
        {
          "name": "Kirodex_0.39.0_amd64.AppImage",
          "downloads": 0,
          "platform": "linux"
        },
        {
          "name": "Kirodex_0.39.0_amd64.AppImage.tar.gz",
          "downloads": 0,
          "platform": "linux"
        },
        {
          "name": "Kirodex_0.39.0_amd64.deb",
          "downloads": 0,
          "platform": "linux"
        },
        {
          "name": "Kirodex_0.39.0_x64-setup.exe",
          "downloads": 1,
          "platform": "windows"
        },
        {
          "name": "Kirodex_0.39.0_x64-setup.nsis.zip",
          "downloads": 0,
          "platform": "windows"
        },
        {
          "name": "Kirodex_aarch64.app.tar.gz",
          "downloads": 1,
          "platform": "macos"
        }
      ]
    },
    {
      "tag": "v0.38.0",
      "published": "2026-04-26T07:33:51Z",
      "total": 4,
      "update_checks": 96,
      "assets": [
        {
          "name": "Kirodex_0.38.0_aarch64.dmg",
          "downloads": 1,
          "platform": "macos"
        },
        {
          "name": "Kirodex_0.38.0_amd64.AppImage",
          "downloads": 0,
          "platform": "linux"
        },
        {
          "name": "Kirodex_0.38.0_amd64.AppImage.tar.gz",
          "downloads": 0,
          "platform": "linux"
        },
        {
          "name": "Kirodex_0.38.0_amd64.deb",
          "downloads": 0,
          "platform": "linux"
        },
        {
          "name": "Kirodex_0.38.0_x64-setup.exe",
          "downloads": 1,
          "platform": "windows"
        },
        {
          "name": "Kirodex_0.38.0_x64-setup.nsis.zip",
          "downloads": 0,
          "platform": "windows"
        },
        {
          "name": "Kirodex_aarch64.app.tar.gz",
          "downloads": 2,
          "platform": "macos"
        }
      ]
    },
    {
      "tag": "v0.37.0",
      "published": "2026-04-25T23:12:14Z",
      "total": 2,
      "update_checks": 14,
      "assets": [
        {
          "name": "Kirodex_0.37.0_aarch64.dmg",
          "downloads": 1,
          "platform": "macos"
        },
        {
          "name": "Kirodex_0.37.0_amd64.AppImage",
          "downloads": 0,
          "platform": "linux"
        },
        {
          "name": "Kirodex_0.37.0_amd64.AppImage.tar.gz",
          "downloads": 0,
          "platform": "linux"
        },
        {
          "name": "Kirodex_0.37.0_amd64.deb",
          "downloads": 0,
          "platform": "linux"
        },
        {
          "name": "Kirodex_0.37.0_x64-setup.exe",
          "downloads": 0,
          "platform": "windows"
        },
        {
          "name": "Kirodex_0.37.0_x64-setup.nsis.zip",
          "downloads": 0,
          "platform": "windows"
        },
        {
          "name": "Kirodex_aarch64.app.tar.gz",
          "downloads": 1,
          "platform": "macos"
        }
      ]
    },
    {
      "tag": "v0.36.0",
      "published": "2026-04-25T19:18:39Z",
      "total": 3,
      "update_checks": 21,
      "assets": [
        {
          "name": "Kirodex_0.36.0_aarch64.dmg",
          "downloads": 1,
          "platform": "macos"
        },
        {
          "name": "Kirodex_0.36.0_amd64.AppImage",
          "downloads": 0,
          "platform": "linux"
        },
        {
          "name": "Kirodex_0.36.0_amd64.AppImage.tar.gz",
          "downloads": 0,
          "platform": "linux"
        },
        {
          "name": "Kirodex_0.36.0_amd64.deb",
          "downloads": 0,
          "platform": "linux"
        },
        {
          "name": "Kirodex_0.36.0_x64-setup.exe",
          "downloads": 1,
          "platform": "windows"
        },
        {
          "name": "Kirodex_0.36.0_x64-setup.nsis.zip",
          "downloads": 0,
          "platform": "windows"
        },
        {
          "name": "Kirodex_aarch64.app.tar.gz",
          "downloads": 1,
          "platform": "macos"
        }
      ]
    },
    {
      "tag": "v0.35.0",
      "published": "2026-04-24T21:14:42Z",
      "total": 6,
      "update_checks": 93,
      "assets": [
        {
          "name": "Kirodex_0.35.0_aarch64.dmg",
          "downloads": 1,
          "platform": "macos"
        },
        {
          "name": "Kirodex_0.35.0_amd64.AppImage",
          "downloads": 0,
          "platform": "linux"
        },
        {
          "name": "Kirodex_0.35.0_amd64.AppImage.tar.gz",
          "downloads": 0,
          "platform": "linux"
        },
        {
          "name": "Kirodex_0.35.0_amd64.deb",
          "downloads": 0,
          "platform": "linux"
        },
        {
          "name": "Kirodex_0.35.0_x64-setup.exe",
          "downloads": 3,
          "platform": "windows"
        },
        {
          "name": "Kirodex_0.35.0_x64-setup.nsis.zip",
          "downloads": 0,
          "platform": "windows"
        },
        {
          "name": "Kirodex_aarch64.app.tar.gz",
          "downloads": 2,
          "platform": "macos"
        }
      ]
    },
    {
      "tag": "v0.34.0",
      "published": "2026-04-24T14:32:36Z",
      "total": 11,
      "update_checks": 45,
      "assets": [
        {
          "name": "Kirodex_0.34.0_aarch64.dmg",
          "downloads": 2,
          "platform": "macos"
        },
        {
          "name": "Kirodex_0.34.0_amd64.AppImage",
          "downloads": 0,
          "platform": "linux"
        },
        {
          "name": "Kirodex_0.34.0_amd64.AppImage.tar.gz",
          "downloads": 0,
          "platform": "linux"
        },
        {
          "name": "Kirodex_0.34.0_amd64.deb",
          "downloads": 1,
          "platform": "linux"
        },
        {
          "name": "Kirodex_0.34.0_x64-setup.exe",
          "downloads": 5,
          "platform": "windows"
        },
        {
          "name": "Kirodex_0.34.0_x64-setup.nsis.zip",
          "downloads": 0,
          "platform": "windows"
        },
        {
          "name": "Kirodex_aarch64.app.tar.gz",
          "downloads": 3,
          "platform": "macos"
        }
      ]
    },
    {
      "tag": "v0.33.2",
      "published": "2026-04-24T08:59:28Z",
      "total": 9,
      "update_checks": 46,
      "assets": [
        {
          "name": "Kirodex_0.33.2_aarch64.dmg",
          "downloads": 4,
          "platform": "macos"
        },
        {
          "name": "Kirodex_0.33.2_amd64.AppImage",
          "downloads": 0,
          "platform": "linux"
        },
        {
          "name": "Kirodex_0.33.2_amd64.AppImage.tar.gz",
          "downloads": 1,
          "platform": "linux"
        },
        {
          "name": "Kirodex_0.33.2_amd64.deb",
          "downloads": 0,
          "platform": "linux"
        },
        {
          "name": "Kirodex_0.33.2_x64-setup.exe",
          "downloads": 0,
          "platform": "windows"
        },
        {
          "name": "Kirodex_0.33.2_x64-setup.nsis.zip",
          "downloads": 1,
          "platform": "windows"
        },
        {
          "name": "Kirodex_aarch64.app.tar.gz",
          "downloads": 3,
          "platform": "macos"
        }
      ]
    },
    {
      "tag": "v0.33.1",
      "published": "2026-04-24T07:30:14Z",
      "total": 2,
      "update_checks": 13,
      "assets": [
        {
          "name": "Kirodex_0.33.1_aarch64.dmg",
          "downloads": 1,
          "platform": "macos"
        },
        {
          "name": "Kirodex_0.33.1_amd64.AppImage",
          "downloads": 0,
          "platform": "linux"
        },
        {
          "name": "Kirodex_0.33.1_amd64.AppImage.tar.gz",
          "downloads": 0,
          "platform": "linux"
        },
        {
          "name": "Kirodex_0.33.1_amd64.deb",
          "downloads": 0,
          "platform": "linux"
        },
        {
          "name": "Kirodex_0.33.1_x64-setup.exe",
          "downloads": 0,
          "platform": "windows"
        },
        {
          "name": "Kirodex_0.33.1_x64-setup.nsis.zip",
          "downloads": 0,
          "platform": "windows"
        },
        {
          "name": "Kirodex_aarch64.app.tar.gz",
          "downloads": 1,
          "platform": "macos"
        }
      ]
    },
    {
      "tag": "v0.33.0",
      "published": "2026-04-24T07:12:43Z",
      "total": 2,
      "update_checks": 3,
      "assets": [
        {
          "name": "Kirodex_0.33.0_aarch64.dmg",
          "downloads": 1,
          "platform": "macos"
        },
        {
          "name": "Kirodex_0.33.0_amd64.AppImage",
          "downloads": 0,
          "platform": "linux"
        },
        {
          "name": "Kirodex_0.33.0_amd64.AppImage.tar.gz",
          "downloads": 0,
          "platform": "linux"
        },
        {
          "name": "Kirodex_0.33.0_amd64.deb",
          "downloads": 0,
          "platform": "linux"
        },
        {
          "name": "Kirodex_0.33.0_x64-setup.exe",
          "downloads": 0,
          "platform": "windows"
        },
        {
          "name": "Kirodex_0.33.0_x64-setup.nsis.zip",
          "downloads": 0,
          "platform": "windows"
        },
        {
          "name": "Kirodex_aarch64.app.tar.gz",
          "downloads": 1,
          "platform": "macos"
        }
      ]
    },
    {
      "tag": "v0.32.0",
      "published": "2026-04-23T09:32:35Z",
      "total": 6,
      "update_checks": 93,
      "assets": [
        {
          "name": "Kirodex_0.32.0_aarch64.dmg",
          "downloads": 4,
          "platform": "macos"
        },
        {
          "name": "Kirodex_0.32.0_amd64.AppImage",
          "downloads": 0,
          "platform": "linux"
        },
        {
          "name": "Kirodex_0.32.0_amd64.AppImage.tar.gz",
          "downloads": 0,
          "platform": "linux"
        },
        {
          "name": "Kirodex_0.32.0_amd64.deb",
          "downloads": 0,
          "platform": "linux"
        },
        {
          "name": "Kirodex_0.32.0_x64-setup.exe",
          "downloads": 1,
          "platform": "windows"
        },
        {
          "name": "Kirodex_0.32.0_x64-setup.nsis.zip",
          "downloads": 0,
          "platform": "windows"
        },
        {
          "name": "Kirodex_aarch64.app.tar.gz",
          "downloads": 1,
          "platform": "macos"
        }
      ]
    },
    {
      "tag": "v0.31.0",
      "published": "2026-04-23T09:26:17Z",
      "total": 1,
      "update_checks": 0,
      "assets": [
        {
          "name": "Kirodex_0.31.0_aarch64.dmg",
          "downloads": 1,
          "platform": "macos"
        },
        {
          "name": "Kirodex_0.31.0_amd64.AppImage",
          "downloads": 0,
          "platform": "linux"
        },
        {
          "name": "Kirodex_0.31.0_amd64.AppImage.tar.gz",
          "downloads": 0,
          "platform": "linux"
        },
        {
          "name": "Kirodex_0.31.0_amd64.deb",
          "downloads": 0,
          "platform": "linux"
        },
        {
          "name": "Kirodex_0.31.0_x64-setup.exe",
          "downloads": 0,
          "platform": "windows"
        },
        {
          "name": "Kirodex_0.31.0_x64-setup.nsis.zip",
          "downloads": 0,
          "platform": "windows"
        },
        {
          "name": "Kirodex_aarch64.app.tar.gz",
          "downloads": 0,
          "platform": "macos"
        }
      ]
    },
    {
      "tag": "v0.30.0",
      "published": "2026-04-23T09:25:47Z",
      "total": 6,
      "update_checks": 0,
      "assets": [
        {
          "name": "Kirodex_0.30.0_aarch64.dmg",
          "downloads": 2,
          "platform": "macos"
        },
        {
          "name": "Kirodex_0.30.0_amd64.AppImage",
          "downloads": 1,
          "platform": "linux"
        },
        {
          "name": "Kirodex_0.30.0_amd64.AppImage.tar.gz",
          "downloads": 1,
          "platform": "linux"
        },
        {
          "name": "Kirodex_0.30.0_amd64.deb",
          "downloads": 1,
          "platform": "linux"
        },
        {
          "name": "Kirodex_0.30.0_x64-setup.exe",
          "downloads": 0,
          "platform": "windows"
        },
        {
          "name": "Kirodex_0.30.0_x64-setup.nsis.zip",
          "downloads": 0,
          "platform": "windows"
        },
        {
          "name": "Kirodex_aarch64.app.tar.gz",
          "downloads": 1,
          "platform": "macos"
        }
      ]
    },
    {
      "tag": "v0.28.0",
      "published": "2026-04-22T12:00:09Z",
      "total": 18,
      "update_checks": 145,
      "assets": [
        {
          "name": "Kirodex-0.28.0-1.x86_64.rpm",
          "downloads": 0,
          "platform": "linux"
        },
        {
          "name": "Kirodex_0.28.0_aarch64.dmg",
          "downloads": 12,
          "platform": "macos"
        },
        {
          "name": "Kirodex_0.28.0_amd64.AppImage",
          "downloads": 0,
          "platform": "linux"
        },
        {
          "name": "Kirodex_0.28.0_amd64.AppImage.tar.gz",
          "downloads": 0,
          "platform": "linux"
        },
        {
          "name": "Kirodex_0.28.0_amd64.deb",
          "downloads": 0,
          "platform": "linux"
        },
        {
          "name": "Kirodex_0.28.0_x64-setup.exe",
          "downloads": 3,
          "platform": "windows"
        },
        {
          "name": "Kirodex_0.28.0_x64-setup.nsis.zip",
          "downloads": 0,
          "platform": "windows"
        },
        {
          "name": "Kirodex_0.28.0_x64_en-US.msi",
          "downloads": 0,
          "platform": "windows"
        },
        {
          "name": "Kirodex_0.28.0_x64_en-US.msi.zip",
          "downloads": 0,
          "platform": "windows"
        },
        {
          "name": "Kirodex_aarch64.app.tar.gz",
          "downloads": 3,
          "platform": "macos"
        }
      ]
    },
    {
      "tag": "v0.27.0",
      "published": "2026-04-22T05:14:26Z",
      "total": 13,
      "update_checks": 43,
      "assets": [
        {
          "name": "Kirodex-0.27.0-1.x86_64.rpm",
          "downloads": 1,
          "platform": "linux"
        },
        {
          "name": "Kirodex_0.27.0_aarch64.dmg",
          "downloads": 5,
          "platform": "macos"
        },
        {
          "name": "Kirodex_0.27.0_amd64.AppImage",
          "downloads": 1,
          "platform": "linux"
        },
        {
          "name": "Kirodex_0.27.0_amd64.AppImage.tar.gz",
          "downloads": 1,
          "platform": "linux"
        },
        {
          "name": "Kirodex_0.27.0_amd64.deb",
          "downloads": 1,
          "platform": "linux"
        },
        {
          "name": "Kirodex_0.27.0_x64-setup.exe",
          "downloads": 1,
          "platform": "windows"
        },
        {
          "name": "Kirodex_0.27.0_x64-setup.nsis.zip",
          "downloads": 0,
          "platform": "windows"
        },
        {
          "name": "Kirodex_0.27.0_x64_en-US.msi",
          "downloads": 0,
          "platform": "windows"
        },
        {
          "name": "Kirodex_0.27.0_x64_en-US.msi.zip",
          "downloads": 0,
          "platform": "windows"
        },
        {
          "name": "Kirodex_aarch64.app.tar.gz",
          "downloads": 3,
          "platform": "macos"
        }
      ]
    },
    {
      "tag": "v0.26.0",
      "published": "2026-04-21T17:50:29Z",
      "total": 3,
      "update_checks": 45,
      "assets": [
        {
          "name": "Kirodex-0.26.0-1.x86_64.rpm",
          "downloads": 0,
          "platform": "linux"
        },
        {
          "name": "Kirodex_0.26.0_aarch64.dmg",
          "downloads": 1,
          "platform": "macos"
        },
        {
          "name": "Kirodex_0.26.0_amd64.AppImage",
          "downloads": 0,
          "platform": "linux"
        },
        {
          "name": "Kirodex_0.26.0_amd64.AppImage.tar.gz",
          "downloads": 0,
          "platform": "linux"
        },
        {
          "name": "Kirodex_0.26.0_amd64.deb",
          "downloads": 0,
          "platform": "linux"
        },
        {
          "name": "Kirodex_0.26.0_x64-setup.exe",
          "downloads": 1,
          "platform": "windows"
        },
        {
          "name": "Kirodex_0.26.0_x64-setup.nsis.zip",
          "downloads": 0,
          "platform": "windows"
        },
        {
          "name": "Kirodex_0.26.0_x64_en-US.msi",
          "downloads": 0,
          "platform": "windows"
        },
        {
          "name": "Kirodex_0.26.0_x64_en-US.msi.zip",
          "downloads": 0,
          "platform": "windows"
        },
        {
          "name": "Kirodex_aarch64.app.tar.gz",
          "downloads": 1,
          "platform": "macos"
        }
      ]
    },
    {
      "tag": "v0.25.0",
      "published": "2026-04-21T15:44:00Z",
      "total": 6,
      "update_checks": 35,
      "assets": [
        {
          "name": "Kirodex-0.25.0-1.x86_64.rpm",
          "downloads": 0,
          "platform": "linux"
        },
        {
          "name": "Kirodex_0.25.0_aarch64.dmg",
          "downloads": 1,
          "platform": "macos"
        },
        {
          "name": "Kirodex_0.25.0_amd64.AppImage",
          "downloads": 0,
          "platform": "linux"
        },
        {
          "name": "Kirodex_0.25.0_amd64.AppImage.tar.gz",
          "downloads": 0,
          "platform": "linux"
        },
        {
          "name": "Kirodex_0.25.0_amd64.deb",
          "downloads": 0,
          "platform": "linux"
        },
        {
          "name": "Kirodex_0.25.0_x64-setup.exe",
          "downloads": 0,
          "platform": "windows"
        },
        {
          "name": "Kirodex_0.25.0_x64-setup.nsis.zip",
          "downloads": 0,
          "platform": "windows"
        },
        {
          "name": "Kirodex_0.25.0_x64_en-US.msi",
          "downloads": 2,
          "platform": "windows"
        },
        {
          "name": "Kirodex_0.25.0_x64_en-US.msi.zip",
          "downloads": 0,
          "platform": "windows"
        },
        {
          "name": "Kirodex_aarch64.app.tar.gz",
          "downloads": 3,
          "platform": "macos"
        }
      ]
    },
    {
      "tag": "v0.20.0",
      "published": "2026-04-21T15:42:26Z",
      "total": 1,
      "update_checks": 0,
      "assets": [
        {
          "name": "Kirodex-0.20.0-1.x86_64.rpm",
          "downloads": 0,
          "platform": "linux"
        },
        {
          "name": "Kirodex_0.20.0_aarch64.dmg",
          "downloads": 1,
          "platform": "macos"
        },
        {
          "name": "Kirodex_0.20.0_amd64.AppImage",
          "downloads": 0,
          "platform": "linux"
        },
        {
          "name": "Kirodex_0.20.0_amd64.AppImage.tar.gz",
          "downloads": 0,
          "platform": "linux"
        },
        {
          "name": "Kirodex_0.20.0_amd64.deb",
          "downloads": 0,
          "platform": "linux"
        },
        {
          "name": "Kirodex_0.20.0_x64-setup.exe",
          "downloads": 0,
          "platform": "windows"
        },
        {
          "name": "Kirodex_0.20.0_x64-setup.nsis.zip",
          "downloads": 0,
          "platform": "windows"
        },
        {
          "name": "Kirodex_0.20.0_x64_en-US.msi",
          "downloads": 0,
          "platform": "windows"
        },
        {
          "name": "Kirodex_0.20.0_x64_en-US.msi.zip",
          "downloads": 0,
          "platform": "windows"
        },
        {
          "name": "Kirodex_aarch64.app.tar.gz",
          "downloads": 0,
          "platform": "macos"
        }
      ]
    },
    {
      "tag": "v0.18.0",
      "published": "2026-04-21T07:16:34Z",
      "total": 1,
      "update_checks": 1,
      "assets": [
        {
          "name": "Kirodex-0.18.0-1.x86_64.rpm",
          "downloads": 0,
          "platform": "linux"
        },
        {
          "name": "Kirodex_0.18.0_aarch64.dmg",
          "downloads": 1,
          "platform": "macos"
        },
        {
          "name": "Kirodex_0.18.0_amd64.AppImage",
          "downloads": 0,
          "platform": "linux"
        },
        {
          "name": "Kirodex_0.18.0_amd64.AppImage.tar.gz",
          "downloads": 0,
          "platform": "linux"
        },
        {
          "name": "Kirodex_0.18.0_amd64.deb",
          "downloads": 0,
          "platform": "linux"
        },
        {
          "name": "Kirodex_0.18.0_x64-setup.exe",
          "downloads": 0,
          "platform": "windows"
        },
        {
          "name": "Kirodex_0.18.0_x64-setup.nsis.zip",
          "downloads": 0,
          "platform": "windows"
        },
        {
          "name": "Kirodex_0.18.0_x64_en-US.msi",
          "downloads": 0,
          "platform": "windows"
        },
        {
          "name": "Kirodex_0.18.0_x64_en-US.msi.zip",
          "downloads": 0,
          "platform": "windows"
        },
        {
          "name": "Kirodex_aarch64.app.tar.gz",
          "downloads": 0,
          "platform": "macos"
        }
      ]
    },
    {
      "tag": "v0.17.0",
      "published": "2026-04-20T22:15:43Z",
      "total": 6,
      "update_checks": 31,
      "assets": [
        {
          "name": "Kirodex-0.17.0-1.x86_64.rpm",
          "downloads": 0,
          "platform": "linux"
        },
        {
          "name": "Kirodex_0.17.0_aarch64.dmg",
          "downloads": 3,
          "platform": "macos"
        },
        {
          "name": "Kirodex_0.17.0_amd64.AppImage",
          "downloads": 0,
          "platform": "linux"
        },
        {
          "name": "Kirodex_0.17.0_amd64.AppImage.tar.gz",
          "downloads": 0,
          "platform": "linux"
        },
        {
          "name": "Kirodex_0.17.0_amd64.deb",
          "downloads": 0,
          "platform": "linux"
        },
        {
          "name": "Kirodex_0.17.0_x64-setup.exe",
          "downloads": 0,
          "platform": "windows"
        },
        {
          "name": "Kirodex_0.17.0_x64-setup.nsis.zip",
          "downloads": 0,
          "platform": "windows"
        },
        {
          "name": "Kirodex_0.17.0_x64_en-US.msi",
          "downloads": 0,
          "platform": "windows"
        },
        {
          "name": "Kirodex_0.17.0_x64_en-US.msi.zip",
          "downloads": 0,
          "platform": "windows"
        },
        {
          "name": "Kirodex_aarch64.app.tar.gz",
          "downloads": 3,
          "platform": "macos"
        }
      ]
    },
    {
      "tag": "v0.16.1",
      "published": "2026-04-20T21:36:37Z",
      "total": 2,
      "update_checks": 5,
      "assets": [
        {
          "name": "Kirodex-0.16.1-1.x86_64.rpm",
          "downloads": 0,
          "platform": "linux"
        },
        {
          "name": "Kirodex_0.16.1_aarch64.dmg",
          "downloads": 1,
          "platform": "macos"
        },
        {
          "name": "Kirodex_0.16.1_amd64.AppImage",
          "downloads": 0,
          "platform": "linux"
        },
        {
          "name": "Kirodex_0.16.1_amd64.AppImage.tar.gz",
          "downloads": 0,
          "platform": "linux"
        },
        {
          "name": "Kirodex_0.16.1_amd64.deb",
          "downloads": 0,
          "platform": "linux"
        },
        {
          "name": "Kirodex_0.16.1_x64-setup.exe",
          "downloads": 0,
          "platform": "windows"
        },
        {
          "name": "Kirodex_0.16.1_x64-setup.nsis.zip",
          "downloads": 0,
          "platform": "windows"
        },
        {
          "name": "Kirodex_0.16.1_x64_en-US.msi",
          "downloads": 0,
          "platform": "windows"
        },
        {
          "name": "Kirodex_0.16.1_x64_en-US.msi.zip",
          "downloads": 0,
          "platform": "windows"
        },
        {
          "name": "Kirodex_aarch64.app.tar.gz",
          "downloads": 1,
          "platform": "macos"
        }
      ]
    },
    {
      "tag": "v0.16.0",
      "published": "2026-04-20T21:28:47Z",
      "total": 1,
      "update_checks": 2,
      "assets": [
        {
          "name": "Kirodex-0.16.0-1.x86_64.rpm",
          "downloads": 0,
          "platform": "linux"
        },
        {
          "name": "Kirodex_0.16.0_aarch64.dmg",
          "downloads": 1,
          "platform": "macos"
        },
        {
          "name": "Kirodex_0.16.0_amd64.AppImage",
          "downloads": 0,
          "platform": "linux"
        },
        {
          "name": "Kirodex_0.16.0_amd64.AppImage.tar.gz",
          "downloads": 0,
          "platform": "linux"
        },
        {
          "name": "Kirodex_0.16.0_amd64.deb",
          "downloads": 0,
          "platform": "linux"
        },
        {
          "name": "Kirodex_0.16.0_x64-setup.exe",
          "downloads": 0,
          "platform": "windows"
        },
        {
          "name": "Kirodex_0.16.0_x64-setup.nsis.zip",
          "downloads": 0,
          "platform": "windows"
        },
        {
          "name": "Kirodex_0.16.0_x64_en-US.msi",
          "downloads": 0,
          "platform": "windows"
        },
        {
          "name": "Kirodex_0.16.0_x64_en-US.msi.zip",
          "downloads": 0,
          "platform": "windows"
        },
        {
          "name": "Kirodex_aarch64.app.tar.gz",
          "downloads": 0,
          "platform": "macos"
        }
      ]
    },
    {
      "tag": "v0.15.0",
      "published": "2026-04-20T20:24:26Z",
      "total": 2,
      "update_checks": 13,
      "assets": [
        {
          "name": "Kirodex-0.15.0-1.x86_64.rpm",
          "downloads": 0,
          "platform": "linux"
        },
        {
          "name": "Kirodex_0.15.0_aarch64.dmg",
          "downloads": 1,
          "platform": "macos"
        },
        {
          "name": "Kirodex_0.15.0_amd64.AppImage",
          "downloads": 0,
          "platform": "linux"
        },
        {
          "name": "Kirodex_0.15.0_amd64.AppImage.tar.gz",
          "downloads": 0,
          "platform": "linux"
        },
        {
          "name": "Kirodex_0.15.0_amd64.deb",
          "downloads": 0,
          "platform": "linux"
        },
        {
          "name": "Kirodex_0.15.0_x64-setup.exe",
          "downloads": 0,
          "platform": "windows"
        },
        {
          "name": "Kirodex_0.15.0_x64-setup.nsis.zip",
          "downloads": 0,
          "platform": "windows"
        },
        {
          "name": "Kirodex_0.15.0_x64_en-US.msi",
          "downloads": 0,
          "platform": "windows"
        },
        {
          "name": "Kirodex_0.15.0_x64_en-US.msi.zip",
          "downloads": 0,
          "platform": "windows"
        },
        {
          "name": "Kirodex_aarch64.app.tar.gz",
          "downloads": 1,
          "platform": "macos"
        }
      ]
    },
    {
      "tag": "v0.14.0",
      "published": "2026-04-18T23:17:05Z",
      "total": 26,
      "update_checks": 258,
      "assets": [
        {
          "name": "Kirodex-0.14.0-1.x86_64.rpm",
          "downloads": 1,
          "platform": "linux"
        },
        {
          "name": "Kirodex_0.14.0_aarch64.dmg",
          "downloads": 11,
          "platform": "macos"
        },
        {
          "name": "Kirodex_0.14.0_amd64.AppImage",
          "downloads": 2,
          "platform": "linux"
        },
        {
          "name": "Kirodex_0.14.0_amd64.AppImage.tar.gz",
          "downloads": 1,
          "platform": "linux"
        },
        {
          "name": "Kirodex_0.14.0_amd64.deb",
          "downloads": 1,
          "platform": "linux"
        },
        {
          "name": "Kirodex_0.14.0_x64-setup.exe",
          "downloads": 3,
          "platform": "windows"
        },
        {
          "name": "Kirodex_0.14.0_x64-setup.nsis.zip",
          "downloads": 0,
          "platform": "windows"
        },
        {
          "name": "Kirodex_0.14.0_x64_en-US.msi",
          "downloads": 2,
          "platform": "windows"
        },
        {
          "name": "Kirodex_0.14.0_x64_en-US.msi.zip",
          "downloads": 0,
          "platform": "windows"
        },
        {
          "name": "Kirodex_aarch64.app.tar.gz",
          "downloads": 5,
          "platform": "macos"
        }
      ]
    },
    {
      "tag": "v0.13.0",
      "published": "2026-04-18T14:14:59Z",
      "total": 6,
      "update_checks": 59,
      "assets": [
        {
          "name": "Kirodex-0.13.0-1.x86_64.rpm",
          "downloads": 0,
          "platform": "linux"
        },
        {
          "name": "Kirodex_0.13.0_aarch64.dmg",
          "downloads": 2,
          "platform": "macos"
        },
        {
          "name": "Kirodex_0.13.0_amd64.AppImage",
          "downloads": 0,
          "platform": "linux"
        },
        {
          "name": "Kirodex_0.13.0_amd64.AppImage.tar.gz",
          "downloads": 0,
          "platform": "linux"
        },
        {
          "name": "Kirodex_0.13.0_amd64.deb",
          "downloads": 0,
          "platform": "linux"
        },
        {
          "name": "Kirodex_0.13.0_x64-setup.exe",
          "downloads": 1,
          "platform": "windows"
        },
        {
          "name": "Kirodex_0.13.0_x64-setup.nsis.zip",
          "downloads": 0,
          "platform": "windows"
        },
        {
          "name": "Kirodex_0.13.0_x64_en-US.msi",
          "downloads": 2,
          "platform": "windows"
        },
        {
          "name": "Kirodex_0.13.0_x64_en-US.msi.zip",
          "downloads": 0,
          "platform": "windows"
        },
        {
          "name": "Kirodex_aarch64.app.tar.gz",
          "downloads": 1,
          "platform": "macos"
        }
      ]
    },
    {
      "tag": "v0.12.0",
      "published": "2026-04-17T21:41:37Z",
      "total": 21,
      "update_checks": 113,
      "assets": [
        {
          "name": "Kirodex-0.12.0-1.x86_64.rpm",
          "downloads": 2,
          "platform": "linux"
        },
        {
          "name": "Kirodex_0.12.0_aarch64.dmg",
          "downloads": 4,
          "platform": "macos"
        },
        {
          "name": "Kirodex_0.12.0_amd64.AppImage",
          "downloads": 2,
          "platform": "linux"
        },
        {
          "name": "Kirodex_0.12.0_amd64.AppImage.tar.gz",
          "downloads": 2,
          "platform": "linux"
        },
        {
          "name": "Kirodex_0.12.0_amd64.deb",
          "downloads": 2,
          "platform": "linux"
        },
        {
          "name": "Kirodex_0.12.0_x64-setup.exe",
          "downloads": 2,
          "platform": "windows"
        },
        {
          "name": "Kirodex_0.12.0_x64-setup.nsis.zip",
          "downloads": 1,
          "platform": "windows"
        },
        {
          "name": "Kirodex_0.12.0_x64_en-US.msi",
          "downloads": 2,
          "platform": "windows"
        },
        {
          "name": "Kirodex_0.12.0_x64_en-US.msi.zip",
          "downloads": 1,
          "platform": "windows"
        },
        {
          "name": "Kirodex_aarch64.app.tar.gz",
          "downloads": 3,
          "platform": "macos"
        }
      ]
    },
    {
      "tag": "v0.11.0",
      "published": "2026-04-16T09:15:54Z",
      "total": 30,
      "update_checks": 169,
      "assets": [
        {
          "name": "Kirodex-0.11.0-1.x86_64.rpm",
          "downloads": 2,
          "platform": "linux"
        },
        {
          "name": "Kirodex_0.11.0_aarch64.dmg",
          "downloads": 13,
          "platform": "macos"
        },
        {
          "name": "Kirodex_0.11.0_amd64.AppImage",
          "downloads": 1,
          "platform": "linux"
        },
        {
          "name": "Kirodex_0.11.0_amd64.AppImage.tar.gz",
          "downloads": 1,
          "platform": "linux"
        },
        {
          "name": "Kirodex_0.11.0_amd64.deb",
          "downloads": 1,
          "platform": "linux"
        },
        {
          "name": "Kirodex_0.11.0_x64-setup.exe",
          "downloads": 4,
          "platform": "windows"
        },
        {
          "name": "Kirodex_0.11.0_x64-setup.nsis.zip",
          "downloads": 1,
          "platform": "windows"
        },
        {
          "name": "Kirodex_0.11.0_x64_en-US.msi",
          "downloads": 3,
          "platform": "windows"
        },
        {
          "name": "Kirodex_0.11.0_x64_en-US.msi.zip",
          "downloads": 1,
          "platform": "windows"
        },
        {
          "name": "Kirodex_aarch64.app.tar.gz",
          "downloads": 3,
          "platform": "macos"
        }
      ]
    },
    {
      "tag": "v0.10.1",
      "published": "2026-04-15T23:01:34Z",
      "total": 26,
      "update_checks": 18,
      "assets": [
        {
          "name": "Kirodex-0.10.1-1.x86_64.rpm",
          "downloads": 2,
          "platform": "linux"
        },
        {
          "name": "Kirodex_0.10.1_aarch64.dmg",
          "downloads": 7,
          "platform": "macos"
        },
        {
          "name": "Kirodex_0.10.1_amd64.AppImage",
          "downloads": 2,
          "platform": "linux"
        },
        {
          "name": "Kirodex_0.10.1_amd64.AppImage.tar.gz",
          "downloads": 2,
          "platform": "linux"
        },
        {
          "name": "Kirodex_0.10.1_amd64.deb",
          "downloads": 2,
          "platform": "linux"
        },
        {
          "name": "Kirodex_0.10.1_x64-setup.exe",
          "downloads": 2,
          "platform": "windows"
        },
        {
          "name": "Kirodex_0.10.1_x64-setup.nsis.zip",
          "downloads": 2,
          "platform": "windows"
        },
        {
          "name": "Kirodex_0.10.1_x64_en-US.msi",
          "downloads": 2,
          "platform": "windows"
        },
        {
          "name": "Kirodex_0.10.1_x64_en-US.msi.zip",
          "downloads": 2,
          "platform": "windows"
        },
        {
          "name": "Kirodex_aarch64.app.tar.gz",
          "downloads": 3,
          "platform": "macos"
        }
      ]
    },
    {
      "tag": "v0.10.0",
      "published": "2026-04-15T22:47:39Z",
      "total": 22,
      "update_checks": 4,
      "assets": [
        {
          "name": "Kirodex-0.10.0-1.x86_64.rpm",
          "downloads": 2,
          "platform": "linux"
        },
        {
          "name": "Kirodex_0.10.0_aarch64.dmg",
          "downloads": 3,
          "platform": "macos"
        },
        {
          "name": "Kirodex_0.10.0_amd64.AppImage",
          "downloads": 2,
          "platform": "linux"
        },
        {
          "name": "Kirodex_0.10.0_amd64.AppImage.tar.gz",
          "downloads": 2,
          "platform": "linux"
        },
        {
          "name": "Kirodex_0.10.0_amd64.deb",
          "downloads": 2,
          "platform": "linux"
        },
        {
          "name": "Kirodex_0.10.0_x64-setup.exe",
          "downloads": 2,
          "platform": "windows"
        },
        {
          "name": "Kirodex_0.10.0_x64-setup.nsis.zip",
          "downloads": 2,
          "platform": "windows"
        },
        {
          "name": "Kirodex_0.10.0_x64_en-US.msi",
          "downloads": 2,
          "platform": "windows"
        },
        {
          "name": "Kirodex_0.10.0_x64_en-US.msi.zip",
          "downloads": 2,
          "platform": "windows"
        },
        {
          "name": "Kirodex_aarch64.app.tar.gz",
          "downloads": 3,
          "platform": "macos"
        }
      ]
    },
    {
      "tag": "v0.9.2",
      "published": "2026-04-15T21:34:47Z",
      "total": 11,
      "update_checks": 15,
      "assets": [
        {
          "name": "Kirodex-0.9.2-1.x86_64.rpm",
          "downloads": 1,
          "platform": "linux"
        },
        {
          "name": "Kirodex_0.9.2_aarch64.dmg",
          "downloads": 2,
          "platform": "macos"
        },
        {
          "name": "Kirodex_0.9.2_amd64.AppImage",
          "downloads": 1,
          "platform": "linux"
        },
        {
          "name": "Kirodex_0.9.2_amd64.AppImage.tar.gz",
          "downloads": 1,
          "platform": "linux"
        },
        {
          "name": "Kirodex_0.9.2_amd64.deb",
          "downloads": 1,
          "platform": "linux"
        },
        {
          "name": "Kirodex_0.9.2_x64-setup.exe",
          "downloads": 1,
          "platform": "windows"
        },
        {
          "name": "Kirodex_0.9.2_x64-setup.nsis.zip",
          "downloads": 1,
          "platform": "windows"
        },
        {
          "name": "Kirodex_0.9.2_x64_en-US.msi",
          "downloads": 1,
          "platform": "windows"
        },
        {
          "name": "Kirodex_0.9.2_x64_en-US.msi.zip",
          "downloads": 1,
          "platform": "windows"
        },
        {
          "name": "Kirodex_aarch64.app.tar.gz",
          "downloads": 1,
          "platform": "macos"
        }
      ]
    },
    {
      "tag": "v0.9.1",
      "published": "2026-04-15T13:18:35Z",
      "total": 12,
      "update_checks": 60,
      "assets": [
        {
          "name": "Kirodex-0.9.1-1.x86_64.rpm",
          "downloads": 1,
          "platform": "linux"
        },
        {
          "name": "Kirodex_0.9.1_aarch64.dmg",
          "downloads": 2,
          "platform": "macos"
        },
        {
          "name": "Kirodex_0.9.1_amd64.AppImage",
          "downloads": 1,
          "platform": "linux"
        },
        {
          "name": "Kirodex_0.9.1_amd64.AppImage.tar.gz",
          "downloads": 1,
          "platform": "linux"
        },
        {
          "name": "Kirodex_0.9.1_amd64.deb",
          "downloads": 1,
          "platform": "linux"
        },
        {
          "name": "Kirodex_0.9.1_x64-setup.exe",
          "downloads": 1,
          "platform": "windows"
        },
        {
          "name": "Kirodex_0.9.1_x64-setup.nsis.zip",
          "downloads": 1,
          "platform": "windows"
        },
        {
          "name": "Kirodex_0.9.1_x64_en-US.msi",
          "downloads": 1,
          "platform": "windows"
        },
        {
          "name": "Kirodex_0.9.1_x64_en-US.msi.zip",
          "downloads": 1,
          "platform": "windows"
        },
        {
          "name": "Kirodex_aarch64.app.tar.gz",
          "downloads": 2,
          "platform": "macos"
        }
      ]
    },
    {
      "tag": "v0.9.0",
      "published": "2026-04-15T12:13:02Z",
      "total": 13,
      "update_checks": 11,
      "assets": [
        {
          "name": "Kirodex-0.9.0-1.x86_64.rpm",
          "downloads": 1,
          "platform": "linux"
        },
        {
          "name": "Kirodex_0.9.0_aarch64.dmg",
          "downloads": 3,
          "platform": "macos"
        },
        {
          "name": "Kirodex_0.9.0_amd64.AppImage",
          "downloads": 1,
          "platform": "linux"
        },
        {
          "name": "Kirodex_0.9.0_amd64.AppImage.tar.gz",
          "downloads": 1,
          "platform": "linux"
        },
        {
          "name": "Kirodex_0.9.0_amd64.deb",
          "downloads": 1,
          "platform": "linux"
        },
        {
          "name": "Kirodex_0.9.0_x64-setup.exe",
          "downloads": 1,
          "platform": "windows"
        },
        {
          "name": "Kirodex_0.9.0_x64-setup.nsis.zip",
          "downloads": 1,
          "platform": "windows"
        },
        {
          "name": "Kirodex_0.9.0_x64_en-US.msi",
          "downloads": 1,
          "platform": "windows"
        },
        {
          "name": "Kirodex_0.9.0_x64_en-US.msi.zip",
          "downloads": 1,
          "platform": "windows"
        },
        {
          "name": "Kirodex_aarch64.app.tar.gz",
          "downloads": 2,
          "platform": "macos"
        }
      ]
    },
    {
      "tag": "v0.8.15",
      "published": "2026-04-15T09:01:20Z",
      "total": 22,
      "update_checks": 29,
      "assets": [
        {
          "name": "Kirodex-0.8.15-1.x86_64.rpm",
          "downloads": 2,
          "platform": "linux"
        },
        {
          "name": "Kirodex_0.8.15_aarch64.dmg",
          "downloads": 3,
          "platform": "macos"
        },
        {
          "name": "Kirodex_0.8.15_amd64.AppImage",
          "downloads": 2,
          "platform": "linux"
        },
        {
          "name": "Kirodex_0.8.15_amd64.AppImage.tar.gz",
          "downloads": 2,
          "platform": "linux"
        },
        {
          "name": "Kirodex_0.8.15_amd64.deb",
          "downloads": 2,
          "platform": "linux"
        },
        {
          "name": "Kirodex_0.8.15_x64-setup.exe",
          "downloads": 2,
          "platform": "windows"
        },
        {
          "name": "Kirodex_0.8.15_x64-setup.nsis.zip",
          "downloads": 2,
          "platform": "windows"
        },
        {
          "name": "Kirodex_0.8.15_x64_en-US.msi",
          "downloads": 2,
          "platform": "windows"
        },
        {
          "name": "Kirodex_0.8.15_x64_en-US.msi.zip",
          "downloads": 2,
          "platform": "windows"
        },
        {
          "name": "Kirodex_aarch64.app.tar.gz",
          "downloads": 3,
          "platform": "macos"
        }
      ]
    },
    {
      "tag": "v0.8.14",
      "published": "2026-04-15T08:41:46Z",
      "total": 12,
      "update_checks": 2,
      "assets": [
        {
          "name": "Kirodex-0.8.14-1.x86_64.rpm",
          "downloads": 1,
          "platform": "linux"
        },
        {
          "name": "Kirodex_0.8.14_aarch64.dmg",
          "downloads": 2,
          "platform": "macos"
        },
        {
          "name": "Kirodex_0.8.14_amd64.AppImage",
          "downloads": 1,
          "platform": "linux"
        },
        {
          "name": "Kirodex_0.8.14_amd64.AppImage.tar.gz",
          "downloads": 1,
          "platform": "linux"
        },
        {
          "name": "Kirodex_0.8.14_amd64.deb",
          "downloads": 1,
          "platform": "linux"
        },
        {
          "name": "Kirodex_0.8.14_x64-setup.exe",
          "downloads": 1,
          "platform": "windows"
        },
        {
          "name": "Kirodex_0.8.14_x64-setup.nsis.zip",
          "downloads": 1,
          "platform": "windows"
        },
        {
          "name": "Kirodex_0.8.14_x64_en-US.msi",
          "downloads": 1,
          "platform": "windows"
        },
        {
          "name": "Kirodex_0.8.14_x64_en-US.msi.zip",
          "downloads": 1,
          "platform": "windows"
        },
        {
          "name": "Kirodex_aarch64.app.tar.gz",
          "downloads": 2,
          "platform": "macos"
        }
      ]
    },
    {
      "tag": "v0.8.13",
      "published": "2026-04-14T20:57:36Z",
      "total": 23,
      "update_checks": 70,
      "assets": [
        {
          "name": "Kirodex-0.8.13-1.x86_64.rpm",
          "downloads": 2,
          "platform": "linux"
        },
        {
          "name": "Kirodex_0.8.13_aarch64.dmg",
          "downloads": 3,
          "platform": "macos"
        },
        {
          "name": "Kirodex_0.8.13_amd64.AppImage",
          "downloads": 2,
          "platform": "linux"
        },
        {
          "name": "Kirodex_0.8.13_amd64.AppImage.tar.gz",
          "downloads": 2,
          "platform": "linux"
        },
        {
          "name": "Kirodex_0.8.13_amd64.deb",
          "downloads": 2,
          "platform": "linux"
        },
        {
          "name": "Kirodex_0.8.13_x64-setup.exe",
          "downloads": 2,
          "platform": "windows"
        },
        {
          "name": "Kirodex_0.8.13_x64-setup.nsis.zip",
          "downloads": 2,
          "platform": "windows"
        },
        {
          "name": "Kirodex_0.8.13_x64_en-US.msi",
          "downloads": 2,
          "platform": "windows"
        },
        {
          "name": "Kirodex_0.8.13_x64_en-US.msi.zip",
          "downloads": 2,
          "platform": "windows"
        },
        {
          "name": "Kirodex_aarch64.app.tar.gz",
          "downloads": 4,
          "platform": "macos"
        }
      ]
    },
    {
      "tag": "v0.8.12",
      "published": "2026-04-14T14:16:51Z",
      "total": 12,
      "update_checks": 20,
      "assets": [
        {
          "name": "Kirodex-0.8.12-1.x86_64.rpm",
          "downloads": 1,
          "platform": "linux"
        },
        {
          "name": "Kirodex_0.8.12_aarch64.dmg",
          "downloads": 2,
          "platform": "macos"
        },
        {
          "name": "Kirodex_0.8.12_amd64.AppImage",
          "downloads": 1,
          "platform": "linux"
        },
        {
          "name": "Kirodex_0.8.12_amd64.AppImage.tar.gz",
          "downloads": 1,
          "platform": "linux"
        },
        {
          "name": "Kirodex_0.8.12_amd64.deb",
          "downloads": 1,
          "platform": "linux"
        },
        {
          "name": "Kirodex_0.8.12_x64-setup.exe",
          "downloads": 1,
          "platform": "windows"
        },
        {
          "name": "Kirodex_0.8.12_x64-setup.nsis.zip",
          "downloads": 1,
          "platform": "windows"
        },
        {
          "name": "Kirodex_0.8.12_x64_en-US.msi",
          "downloads": 1,
          "platform": "windows"
        },
        {
          "name": "Kirodex_0.8.12_x64_en-US.msi.zip",
          "downloads": 1,
          "platform": "windows"
        },
        {
          "name": "Kirodex_aarch64.app.tar.gz",
          "downloads": 2,
          "platform": "macos"
        }
      ]
    },
    {
      "tag": "v0.8.11",
      "published": "2026-04-13T22:06:17Z",
      "total": 22,
      "update_checks": 22,
      "assets": [
        {
          "name": "Kirodex-0.8.11-1.x86_64.rpm",
          "downloads": 2,
          "platform": "linux"
        },
        {
          "name": "Kirodex_0.8.11_aarch64.dmg",
          "downloads": 4,
          "platform": "macos"
        },
        {
          "name": "Kirodex_0.8.11_amd64.AppImage",
          "downloads": 2,
          "platform": "linux"
        },
        {
          "name": "Kirodex_0.8.11_amd64.AppImage.tar.gz",
          "downloads": 2,
          "platform": "linux"
        },
        {
          "name": "Kirodex_0.8.11_amd64.deb",
          "downloads": 2,
          "platform": "linux"
        },
        {
          "name": "Kirodex_0.8.11_x64-setup.exe",
          "downloads": 2,
          "platform": "windows"
        },
        {
          "name": "Kirodex_0.8.11_x64-setup.nsis.zip",
          "downloads": 2,
          "platform": "windows"
        },
        {
          "name": "Kirodex_0.8.11_x64_en-US.msi",
          "downloads": 2,
          "platform": "windows"
        },
        {
          "name": "Kirodex_0.8.11_x64_en-US.msi.zip",
          "downloads": 2,
          "platform": "windows"
        },
        {
          "name": "Kirodex_aarch64.app.tar.gz",
          "downloads": 2,
          "platform": "macos"
        }
      ]
    },
    {
      "tag": "v0.8.10",
      "published": "2026-04-13T06:37:46Z",
      "total": 27,
      "update_checks": 23,
      "assets": [
        {
          "name": "Kirodex-0.8.10-1.x86_64.rpm",
          "downloads": 2,
          "platform": "linux"
        },
        {
          "name": "Kirodex_0.8.10_aarch64.dmg",
          "downloads": 10,
          "platform": "macos"
        },
        {
          "name": "Kirodex_0.8.10_amd64.AppImage",
          "downloads": 2,
          "platform": "linux"
        },
        {
          "name": "Kirodex_0.8.10_amd64.AppImage.tar.gz",
          "downloads": 2,
          "platform": "linux"
        },
        {
          "name": "Kirodex_0.8.10_amd64.deb",
          "downloads": 2,
          "platform": "linux"
        },
        {
          "name": "Kirodex_0.8.10_x64-setup.exe",
          "downloads": 2,
          "platform": "windows"
        },
        {
          "name": "Kirodex_0.8.10_x64-setup.nsis.zip",
          "downloads": 2,
          "platform": "windows"
        },
        {
          "name": "Kirodex_0.8.10_x64_en-US.msi",
          "downloads": 2,
          "platform": "windows"
        },
        {
          "name": "Kirodex_0.8.10_x64_en-US.msi.zip",
          "downloads": 1,
          "platform": "windows"
        },
        {
          "name": "Kirodex_aarch64.app.tar.gz",
          "downloads": 2,
          "platform": "macos"
        }
      ]
    },
    {
      "tag": "v0.8.9",
      "published": "2026-04-12T19:52:44Z",
      "total": 15,
      "update_checks": 15,
      "assets": [
        {
          "name": "Kirodex-0.8.9-1.x86_64.rpm",
          "downloads": 1,
          "platform": "linux"
        },
        {
          "name": "Kirodex_0.8.9_aarch64.dmg",
          "downloads": 6,
          "platform": "macos"
        },
        {
          "name": "Kirodex_0.8.9_amd64.AppImage",
          "downloads": 1,
          "platform": "linux"
        },
        {
          "name": "Kirodex_0.8.9_amd64.AppImage.tar.gz",
          "downloads": 1,
          "platform": "linux"
        },
        {
          "name": "Kirodex_0.8.9_amd64.deb",
          "downloads": 1,
          "platform": "linux"
        },
        {
          "name": "Kirodex_0.8.9_x64-setup.exe",
          "downloads": 1,
          "platform": "windows"
        },
        {
          "name": "Kirodex_0.8.9_x64-setup.nsis.zip",
          "downloads": 1,
          "platform": "windows"
        },
        {
          "name": "Kirodex_0.8.9_x64_en-US.msi",
          "downloads": 1,
          "platform": "windows"
        },
        {
          "name": "Kirodex_0.8.9_x64_en-US.msi.zip",
          "downloads": 1,
          "platform": "windows"
        },
        {
          "name": "Kirodex_aarch64.app.tar.gz",
          "downloads": 1,
          "platform": "macos"
        }
      ]
    },
    {
      "tag": "v0.8.8",
      "published": "2026-04-11T20:48:00Z",
      "total": 17,
      "update_checks": 37,
      "assets": [
        {
          "name": "Kirodex-0.8.8-1.x86_64.rpm",
          "downloads": 2,
          "platform": "linux"
        },
        {
          "name": "Kirodex_0.8.8_aarch64.dmg",
          "downloads": 3,
          "platform": "macos"
        },
        {
          "name": "Kirodex_0.8.8_amd64.AppImage",
          "downloads": 2,
          "platform": "linux"
        },
        {
          "name": "Kirodex_0.8.8_amd64.deb",
          "downloads": 2,
          "platform": "linux"
        },
        {
          "name": "Kirodex_0.8.8_x64-setup.exe",
          "downloads": 3,
          "platform": "windows"
        },
        {
          "name": "Kirodex_0.8.8_x64_en-US.msi",
          "downloads": 2,
          "platform": "windows"
        },
        {
          "name": "Kirodex_aarch64.app.tar.gz",
          "downloads": 3,
          "platform": "macos"
        }
      ]
    },
    {
      "tag": "v0.8.7",
      "published": "2026-04-11T20:24:05Z",
      "total": 10,
      "update_checks": 3,
      "assets": [
        {
          "name": "Kirodex-0.8.7-1.x86_64.rpm",
          "downloads": 1,
          "platform": "linux"
        },
        {
          "name": "Kirodex_0.8.7_aarch64.dmg",
          "downloads": 4,
          "platform": "macos"
        },
        {
          "name": "Kirodex_0.8.7_amd64.AppImage",
          "downloads": 1,
          "platform": "linux"
        },
        {
          "name": "Kirodex_0.8.7_amd64.deb",
          "downloads": 1,
          "platform": "linux"
        },
        {
          "name": "Kirodex_0.8.7_x64-setup.exe",
          "downloads": 1,
          "platform": "windows"
        },
        {
          "name": "Kirodex_0.8.7_x64_en-US.msi",
          "downloads": 1,
          "platform": "windows"
        },
        {
          "name": "Kirodex_aarch64.app.tar.gz",
          "downloads": 1,
          "platform": "macos"
        }
      ]
    },
    {
      "tag": "v0.8.6",
      "published": "2026-04-11T20:01:24Z",
      "total": 8,
      "update_checks": 1,
      "assets": [
        {
          "name": "Kirodex-0.8.6-1.x86_64.rpm",
          "downloads": 1,
          "platform": "linux"
        },
        {
          "name": "Kirodex_0.8.6_aarch64.dmg",
          "downloads": 2,
          "platform": "macos"
        },
        {
          "name": "Kirodex_0.8.6_amd64.AppImage",
          "downloads": 1,
          "platform": "linux"
        },
        {
          "name": "Kirodex_0.8.6_amd64.deb",
          "downloads": 1,
          "platform": "linux"
        },
        {
          "name": "Kirodex_0.8.6_x64-setup.exe",
          "downloads": 1,
          "platform": "windows"
        },
        {
          "name": "Kirodex_0.8.6_x64_en-US.msi",
          "downloads": 1,
          "platform": "windows"
        },
        {
          "name": "Kirodex_aarch64.app.tar.gz",
          "downloads": 1,
          "platform": "macos"
        }
      ]
    },
    {
      "tag": "v0.8.4",
      "published": "2026-04-11T16:47:16Z",
      "total": 15,
      "update_checks": 0,
      "assets": [
        {
          "name": "Kirodex-0.8.4-1.x86_64.rpm",
          "downloads": 2,
          "platform": "linux"
        },
        {
          "name": "Kirodex_0.8.4_aarch64.dmg",
          "downloads": 3,
          "platform": "macos"
        },
        {
          "name": "Kirodex_0.8.4_amd64.AppImage",
          "downloads": 2,
          "platform": "linux"
        },
        {
          "name": "Kirodex_0.8.4_amd64.deb",
          "downloads": 2,
          "platform": "linux"
        },
        {
          "name": "Kirodex_0.8.4_x64-setup.exe",
          "downloads": 2,
          "platform": "windows"
        },
        {
          "name": "Kirodex_0.8.4_x64_en-US.msi",
          "downloads": 2,
          "platform": "windows"
        },
        {
          "name": "Kirodex_aarch64.app.tar.gz",
          "downloads": 2,
          "platform": "macos"
        }
      ]
    },
    {
      "tag": "v0.8.3",
      "published": "2026-04-11T15:03:42Z",
      "total": 10,
      "update_checks": 0,
      "assets": [
        {
          "name": "Kirodex-0.8.3-1.x86_64.rpm",
          "downloads": 1,
          "platform": "linux"
        },
        {
          "name": "Kirodex_0.8.3_aarch64.dmg",
          "downloads": 4,
          "platform": "macos"
        },
        {
          "name": "Kirodex_0.8.3_amd64.AppImage",
          "downloads": 1,
          "platform": "linux"
        },
        {
          "name": "Kirodex_0.8.3_amd64.deb",
          "downloads": 1,
          "platform": "linux"
        },
        {
          "name": "Kirodex_0.8.3_x64-setup.exe",
          "downloads": 1,
          "platform": "windows"
        },
        {
          "name": "Kirodex_0.8.3_x64_en-US.msi",
          "downloads": 1,
          "platform": "windows"
        },
        {
          "name": "Kirodex_aarch64.app.tar.gz",
          "downloads": 1,
          "platform": "macos"
        }
      ]
    },
    {
      "tag": "v0.8.1",
      "published": "2026-04-11T14:48:23Z",
      "total": 10,
      "update_checks": 0,
      "assets": [
        {
          "name": "Kirodex-0.8.1-1.x86_64.rpm",
          "downloads": 1,
          "platform": "linux"
        },
        {
          "name": "Kirodex_0.8.1_aarch64.dmg",
          "downloads": 5,
          "platform": "macos"
        },
        {
          "name": "Kirodex_0.8.1_amd64.AppImage",
          "downloads": 1,
          "platform": "linux"
        },
        {
          "name": "Kirodex_0.8.1_amd64.deb",
          "downloads": 1,
          "platform": "linux"
        },
        {
          "name": "Kirodex_0.8.1_x64-setup.exe",
          "downloads": 1,
          "platform": "windows"
        },
        {
          "name": "Kirodex_0.8.1_x64_en-US.msi",
          "downloads": 1,
          "platform": "windows"
        }
      ]
    }
  ],
  "totals": {
    "all": 484,
    "update_checks": 1739,
    "macos": 230,
    "windows": 131,
    "linux": 123
  },
  "homebrew_tap": null
}
